{ "height":75,
 "infinite":false,
 "layers":[
        {
         "draworder":"topdown",
         "id":2,
         "name":"objects",
         "objects":[
                {
                 "height":80,
                 "id":32,
                 "name":"studs",
                 "rotation":0,
                 "type":"",
                 "visible":true,
                 "width":80,
                 "x":30,
                 "y":1460
                }, 
                {
                 "height":80,
                 "id":50,
                 "name":"studs",
                 "rotation":0,
                 "type":"",
                 "visible":true,
                 "width":80,
                 "x":50,
                 "y":480
                }, 
                {
                 "height":80,
                 "id":51,
                 "name":"studs",
                 "rotation":0,
                 "type":"",
                 "visible":true,
                 "width":80,
                 "x":150,
                 "y":2790
                }, 
                {
                 "height":80,
                 "id":54,
                 "name":"studs",
                 "rotation":0,
                 "type":"",
                 "visible":true,
                 "width":80,
                 "x":40,
                 "y":2250
                }, 
                {
                 "height":40,
                 "id":55,
                 "name":"powerup",
                 "rotation":0,
                 "type":"",
                 "visible":true,
                 "width":40,
                 "x":160,
                 "y":990
                }],
         "opacity":1,
         "type":"objectgroup",
         "visible":true,
         "x":0,
         "y":0
        }, 
        {
         "draworder":"topdown",
         "id":3,
         "name":"obstacles",
         "objects":[
                {
                 "gid":9,
                 "height":602,
                 "id":42,
                 "name":"",
                 "rotation":0,
                 "type":"",
                 "visible":true,
                 "width":635,
                 "x":130,
                 "y":2420
                }, 
                {
                 "gid":5,
                 "height":565,
                 "id":43,
                 "name":"",
                 "rotation":0,
                 "type":"",
                 "visible":true,
                 "width":553,
                 "x":-360,
                 "y":2890
                }, 
                {
                 "gid":8,
                 "height":840,
                 "id":44,
                 "name":"",
                 "rotation":0,
                 "type":"",
                 "visible":true,
                 "width":527,
                 "x":-300,
                 "y":1510
                }, 
                {
                 "gid":7,
                 "height":454,
                 "id":46,
                 "name":"",
                 "rotation":0,
                 "type":"",
                 "visible":true,
                 "width":441,
                 "x":240,
                 "y":660
                }, 
                {
                 "gid":9,
                 "height":602,
                 "id":52,
                 "name":"",
                 "rotation":0,
                 "type":"",
                 "visible":true,
                 "width":635,
                 "x":130,
                 "y":2080
                }],
         "opacity":1,
         "type":"objectgroup",
         "visible":true,
         "x":0,
         "y":0
        }],
 "nextlayerid":4,
 "nextobjectid":56,
 "orientation":"orthogonal",
 "renderorder":"right-down",
 "tiledversion":"1.2.4",
 "tileheight":40,
 "tilesets":[
        {
         "firstgid":1,
         "source":"..\/obstacles-tileset.json"
        }],
 "tilewidth":40,
 "type":"map",
 "version":1.2,
 "width":9
}